robolearn_gym_envs/__init__.py
robolearn_gym_envs-0.0.0.dist-info/LICENSE
robolearn_gym_envs-0.0.0.dist-info/METADATA
robolearn_gym_envs-0.0.0.dist-info/WHEEL
robolearn_gym_envs-0.0.0.dist-info/top_level.txt
robolearn_gym_envs-0.0.0.dist-info/RECORD
